<?xml version="1.0"?>
<mujoco model="scene_10">
	<compiler angle="radian" />
	<include file="include/settings.xml" />
	<asset>
		<include file="include/assets.xml" />
		<include file="robot/include/robot_assets.xml" />
	</asset>
	<include file="include/defaults.xml" />
	<include file="include/custom_attributes_for_shelf_1.xml" />
	<custom>
		<text name="problemName" data="parallel2" />
	</custom>
	<worldbody>
		<include file="include/camera_and_lighting.xml" />
		<body name="object_1" pos="1.749980 0.069742 0.478161" quat="-0.771885 0.000000 0.000000 0.635762">
			<geom contype="3" conaffinity="3" friction="0.4 0.4 0.8" mass="10" name="object_1" rgba="1 0 0. 1" size="0.03 0.05" type="cylinder" />
			<joint armature="0" damping="0" limited="false" name="object_1_free" type="free" />
		</body>
		<body name="object_2" pos="1.585073 -0.275724 0.478161" quat="0.998172 -0.000000 -0.000000 -0.060430">
			<geom contype="3" conaffinity="3" friction="0.4 0.4 0.8" mass="10" name="object_2" rgba="1 0 0. 1" size="0.03 0.05" type="cylinder" />
			<joint armature="0" damping="0" limited="false" name="object_2_free" type="free" />
		</body>
		<body name="object_3" pos="1.747962 -0.136803 0.478161" quat="0.961673 -0.000000 -0.000000 -0.274199">
			<geom contype="3" conaffinity="3" friction="0.4 0.4 0.8" mass="10" name="object_3" rgba="0 1 0. 1" size="0.03 0.05" type="cylinder" />
			<joint armature="0" damping="0" limited="false" name="object_3_free" type="free" />
		</body>
		<body name="object_4" pos="1.544620 -0.113128 0.478161" quat="-0.482933 0.000000 0.000000 0.875657">
			<geom contype="3" conaffinity="3" friction="0.4 0.4 0.8" mass="10" name="object_4" rgba="1 0 0. 1" size="0.03 0.05" type="cylinder" />
			<joint armature="0" damping="0" limited="false" name="object_4_free" type="free" />
		</body>
		<body name="object_5" pos="1.583455 -0.033060 0.478161" quat="0.964867 0.000000 0.000000 0.262738">
			<geom contype="3" conaffinity="3" friction="0.4 0.4 0.8" mass="10" name="object_5" rgba="1 0 0. 1" size="0.03 0.05" type="cylinder" />
			<joint armature="0" damping="0" limited="false" name="object_5_free" type="free" />
		</body>
		<body name="object_6" pos="1.494243 0.207559 0.478161" quat="-0.606640 -0.000000 -0.000000 -0.794977">
			<geom contype="3" conaffinity="3" friction="0.4 0.4 0.8" mass="10" name="object_6" rgba="1 0 0. 1" size="0.03 0.05" type="cylinder" />
			<joint armature="0" damping="0" limited="false" name="object_6_free" type="free" />
		</body>
		<body name="object_7" pos="1.654806 -0.136841 0.478161" quat="0.907914 -0.000000 -0.000000 -0.419157">
			<geom contype="3" conaffinity="3" friction="0.4 0.4 0.8" mass="10" name="object_7" rgba="1 0 0. 1" size="0.03 0.05" type="cylinder" />
			<joint armature="0" damping="0" limited="false" name="object_7_free" type="free" />
		</body>
		<body name="object_8" pos="1.649687 -0.262148 0.478161" quat="0.996560 -0.000000 -0.000000 -0.082873">
			<geom contype="3" conaffinity="3" friction="0.4 0.4 0.8" mass="10" name="object_8" rgba="1 0 0. 1" size="0.03 0.05" type="cylinder" />
			<joint armature="0" damping="0" limited="false" name="object_8_free" type="free" />
		</body>
		<body name="object_9" pos="1.452798 0.076726 0.478161" quat="0.154212 -0.000000 -0.000000 -0.988038">
			<geom contype="3" conaffinity="3" friction="0.4 0.4 0.8" mass="10" name="object_9" rgba="1 0 0. 1" size="0.03 0.05" type="cylinder" />
			<joint armature="0" damping="0" limited="false" name="object_9_free" type="free" />
		</body>
		<body name="object_10" pos="1.473678 -0.177739 0.478161" quat="0.878881 -0.000000 -0.000000 -0.477040">
			<geom contype="3" conaffinity="3" friction="0.4 0.4 0.8" mass="10" name="object_10" rgba="1 0 0. 1" size="0.03 0.05" type="cylinder" />
			<joint armature="0" damping="0" limited="false" name="object_10_free" type="free" />
		</body>
		<include file="robot/include/full_planar_robot.xml" />
		<include file="include/shelf_1.xml" />
		<include file="include/table.xml" />
	</worldbody>
</mujoco>
